jsonpath/__init__.py
jsonpath/cli.py
jsonpath/core.py
jsonpath/grammar.lark
jsonpath/lark.py
jsonpath/lark_parser.py
jsonpath/parser.py
jsonpath/py.typed
jsonpath/transformer.py
jsonpath_build.py
jsonpath_extractor-0.9.2.dist-info/entry_points.txt
jsonpath_extractor-0.9.2.dist-info/WHEEL
jsonpath_extractor-0.9.2.dist-info/METADATA
jsonpath_extractor-0.9.2.dist-info/licenses/LICENSE
jsonpath_extractor-0.9.2.dist-info/RECORD
