Metadata-Version: 2.1
Name: jsonpath-extractor
Version: 0.9.2
Summary: A selector expression for extracting data from JSON.
License: MIT
Keywords: data-extractor,data-extraction,jsonpath,json
Author-email: 林玮 (Jade Lin) <linw1995@icloud.com>
Requires-Python: >=3.9
Classifier: Development Status :: 5 - Production/Stable
Classifier: Intended Audience :: Developers
Classifier: License :: OSI Approved :: MIT License
Classifier: Operating System :: MacOS :: MacOS X
Classifier: Operating System :: Microsoft :: Windows
Classifier: Operating System :: POSIX
Classifier: Programming Language :: Python
Classifier: Programming Language :: Python :: 3
Classifier: Programming Language :: Python :: 3.10
Classifier: Programming Language :: Python :: 3.11
Classifier: Programming Language :: Python :: 3.12
Classifier: Programming Language :: Python :: 3.13
Classifier: Programming Language :: Python :: 3.9
Requires-Dist: typing-extensions~=4.7
Provides-Extra: parser
Requires-Dist: lark~=1.2; extra == "parser"
Project-URL: documentation, https://jsonpath.rtfd.io/en/latest/
Project-URL: homepage, https://github.com/linw1995/jsonpath
Project-URL: repository, https://github.com/linw1995/jsonpath
